slcpy/__init__.py
slcpy/build_graph.py
slcpy/build_semantic.py
slcpy/main.py
slcpy/stitch_images.py
slcpy/version.py
slcpy/utils/__init__.py
slcpy/utils/build_label_mask.py
slcpy/utils/import_data.py
slcpy/utils/interpolation.py
slcpy/utils/stitch.py
slcpy/utils/trim.py
slcpy-0.3.6.dist-info/AUTHORS.rst
slcpy-0.3.6.dist-info/LICENSE
slcpy-0.3.6.dist-info/METADATA
slcpy-0.3.6.dist-info/WHEEL
slcpy-0.3.6.dist-info/entry_points.txt
slcpy-0.3.6.dist-info/top_level.txt
slcpy-0.3.6.dist-info/RECORD
