Metadata-Version: 2.1
Name: slcpy
Version: 0.3.6
Summary: Python package to decode Amira 3D coordinate spatial graphs into semantic label mask
Home-page: https://github.com/SMLC-NYSBC/Semantic_Label_Creator
Author: Robert Kiewisz
Author-email: robert.kiewisz@gmail.com
License: GNU General Public License v3
Keywords: slcpy
Platform: UNKNOWN
Classifier: Development Status :: 5 - Production/Stable
Classifier: Intended Audience :: Developers
Classifier: License :: OSI Approved :: GNU General Public License v3 (GPLv3)
Classifier: Natural Language :: English
Classifier: Programming Language :: Python :: 3.8
Requires-Python: >=3.7
License-File: LICENSE
License-File: AUTHORS.rst
Requires-Dist: click (>=8.0.3)
Requires-Dist: setuptools (>=57.1.0)
Requires-Dist: scikit-image (>=0.19.1)
Requires-Dist: numpy (>=1.20.0)
Requires-Dist: tifffile (>=2021.7.2)
Requires-Dist: tqdm (>=4.62.3)
Requires-Dist: imagecodecs (>=2021.8.26)
Requires-Dist: opencv-python (>=4.5.4.60)
Requires-Dist: scipy (>=1.7.3)
Requires-Dist: open3d (>=0.14.1)
